ni_measurement_service/__init__.py
ni_measurement_service/_internal/__init__.py
ni_measurement_service/_internal/discovery_client.py
ni_measurement_service/_internal/grpc_servicer.py
ni_measurement_service/_internal/parameter/__init__.py
ni_measurement_service/_internal/parameter/metadata.py
ni_measurement_service/_internal/parameter/serialization_strategy.py
ni_measurement_service/_internal/parameter/serializer.py
ni_measurement_service/_internal/service_manager.py
ni_measurement_service/_internal/stubs/__init__.py
ni_measurement_service/_internal/stubs/ni/__init__.py
ni_measurement_service/_internal/stubs/ni/measurementlink/__init__.py
ni_measurement_service/_internal/stubs/ni/measurementlink/discovery/__init__.py
ni_measurement_service/_internal/stubs/ni/measurementlink/discovery/v1/__init__.py
ni_measurement_service/_internal/stubs/ni/measurementlink/discovery/v1/discovery_service_pb2.py
ni_measurement_service/_internal/stubs/ni/measurementlink/discovery/v1/discovery_service_pb2.pyi
ni_measurement_service/_internal/stubs/ni/measurementlink/discovery/v1/discovery_service_pb2_grpc.py
ni_measurement_service/_internal/stubs/ni/measurementlink/measurement/__init__.py
ni_measurement_service/_internal/stubs/ni/measurementlink/measurement/v1/__init__.py
ni_measurement_service/_internal/stubs/ni/measurementlink/measurement/v1/measurement_service_pb2.py
ni_measurement_service/_internal/stubs/ni/measurementlink/measurement/v1/measurement_service_pb2.pyi
ni_measurement_service/_internal/stubs/ni/measurementlink/measurement/v1/measurement_service_pb2_grpc.py
ni_measurement_service/_internal/stubs/ni/measurementlink/pin_map_context_pb2.py
ni_measurement_service/_internal/stubs/ni/measurementlink/pin_map_context_pb2.pyi
ni_measurement_service/_internal/stubs/ni/measurementlink/pin_map_context_pb2_grpc.py
ni_measurement_service/_internal/stubs/ni/measurementlink/pinmap/__init__.py
ni_measurement_service/_internal/stubs/ni/measurementlink/pinmap/v1/__init__.py
ni_measurement_service-0.11.1.dist-info/LICENSE
ni_measurement_service-0.11.1.dist-info/WHEEL
ni_measurement_service-0.11.1.dist-info/METADATA
ni_measurement_service-0.11.1.dist-info/RECORD
