Metadata-Version: 2.1
Name: ni-measurement-service
Version: 0.11.1
Summary: MeasurementLink Support for Python
Home-page: https://github.com/ni/measurement-services-python/
License: MIT
Author: NI
Author-email: opensource@ni.com
Requires-Python: >=3.8,<4.0
Classifier: License :: OSI Approved :: MIT License
Classifier: Programming Language :: Python :: 3
Classifier: Programming Language :: Python :: 3.8
Classifier: Programming Language :: Python :: 3.9
Classifier: Programming Language :: Python :: 3.10
Classifier: Programming Language :: Python :: 3.11
Requires-Dist: grpcio (>=1.41.1,<2.0.0)
Requires-Dist: protobuf (>=3.20,<4.0)
Requires-Dist: pywin32 (>=303,<304); sys_platform == "win32"
Project-URL: Repository, https://github.com/ni/measurement-services-python/
